odoo/addons/sale_stock_available_to_promise_release_block/README.rst
odoo/addons/sale_stock_available_to_promise_release_block/__init__.py
odoo/addons/sale_stock_available_to_promise_release_block/__manifest__.py
odoo/addons/sale_stock_available_to_promise_release_block/hooks.py
odoo/addons/sale_stock_available_to_promise_release_block/i18n/it.po
odoo/addons/sale_stock_available_to_promise_release_block/i18n/sale_stock_available_to_promise_release_block.pot
odoo/addons/sale_stock_available_to_promise_release_block/migrations/16.0.1.1.0/pre-migrate.py
odoo/addons/sale_stock_available_to_promise_release_block/models/__init__.py
odoo/addons/sale_stock_available_to_promise_release_block/models/sale_order.py
odoo/addons/sale_stock_available_to_promise_release_block/models/sale_order_line.py
odoo/addons/sale_stock_available_to_promise_release_block/models/stock_move.py
odoo/addons/sale_stock_available_to_promise_release_block/models/stock_rule.py
odoo/addons/sale_stock_available_to_promise_release_block/readme/CONTRIBUTORS.rst
odoo/addons/sale_stock_available_to_promise_release_block/readme/DESCRIPTION.rst
odoo/addons/sale_stock_available_to_promise_release_block/readme/USAGE.rst
odoo/addons/sale_stock_available_to_promise_release_block/security/ir.model.access.csv
odoo/addons/sale_stock_available_to_promise_release_block/static/description/icon.png
odoo/addons/sale_stock_available_to_promise_release_block/static/description/index.html
odoo/addons/sale_stock_available_to_promise_release_block/tests/__init__.py
odoo/addons/sale_stock_available_to_promise_release_block/tests/test_sale_block_release.py
odoo/addons/sale_stock_available_to_promise_release_block/views/sale_order.xml
odoo/addons/sale_stock_available_to_promise_release_block/views/sale_order_line.xml
odoo/addons/sale_stock_available_to_promise_release_block/views/stock_move.xml
odoo/addons/sale_stock_available_to_promise_release_block/wizards/__init__.py
odoo_addon_sale_stock_available_to_promise_release_block-16.0.1.1.1.dist-info/METADATA
odoo_addon_sale_stock_available_to_promise_release_block-16.0.1.1.1.dist-info/WHEEL
odoo_addon_sale_stock_available_to_promise_release_block-16.0.1.1.1.dist-info/top_level.txt
odoo_addon_sale_stock_available_to_promise_release_block-16.0.1.1.1.dist-info/RECORD
