Metadata-Version: 2.1
Name: odoo-addon-sale_stock_available_to_promise_release_block
Version: 16.0.1.1.1
Summary: Block release of deliveries from sales orders.
Home-page: https://github.com/OCA/wms
Author: Camptcamp, ACSONE SA/NV, BCIM, Odoo Community Association (OCA)
Author-email: support@odoo-community.org
License: AGPL-3
Classifier: Programming Language :: Python
Classifier: Framework :: Odoo
Classifier: Framework :: Odoo :: 16.0
Classifier: License :: OSI Approved :: GNU Affero General Public License v3
Requires-Python: >=3.10
Requires-Dist: odoo-addon-sale-stock-available-to-promise-release<16.1dev,>=16.0dev
Requires-Dist: odoo-addon-stock-available-to-promise-release-block<16.1dev,>=16.0dev
Requires-Dist: odoo<16.1dev,>=16.0a
